aps2mqtt/__init__.py
aps2mqtt/__main__.py
aps2mqtt/config.py
aps2mqtt/main.py
aps2mqtt/mqtthandler.py
aps2mqtt/apsystems/APSystemsSocket.py
aps2mqtt/apsystems/ECU.py
aps2mqtt/apsystems/__init__.py
aps2mqtt-2.0.2.dist-info/licenses/LICENSE
aps2mqtt-2.0.2.dist-info/METADATA
aps2mqtt-2.0.2.dist-info/WHEEL
aps2mqtt-2.0.2.dist-info/top_level.txt
aps2mqtt-2.0.2.dist-info/RECORD
