Metadata-Version: 2.4
Name: aps2mqtt
Version: 2.0.2
Summary: Access APSystems ECU data over MQTT
Author-email: Florian Ligneul <contact@florian-ligneul.fr>
License-Expression: GPL-3.0-or-later
Project-URL: Homepage, https://github.com/fligneul/aps2mqtt
Keywords: mqtt,ap-systems,ecu,iot,solar,home-automation
Classifier: Operating System :: OS Independent
Classifier: Programming Language :: Python :: 3
Classifier: Programming Language :: Python :: 3.9
Classifier: Programming Language :: Python :: 3.10
Classifier: Programming Language :: Python :: 3.11
Classifier: Programming Language :: Python :: 3.12
Classifier: Programming Language :: Python :: 3.13
Classifier: Topic :: Home Automation
Requires-Python: <3.14,>=3.9
License-File: LICENSE
Requires-Dist: requests~=2.32
Requires-Dist: paho.mqtt~=2.1
Requires-Dist: pyyaml~=6.0
Requires-Dist: numpy~=2.3
Requires-Dist: suntime~=1.2
Requires-Dist: str2bool~=1.1
Requires-Dist: tzdata>=2025.2
Dynamic: license-file
